AutoChromedriver/__init__.py
AutoChromedriver/autochromedriver.py
AutoChromedriver/chromedriver_lib.py
AutoChromedriver/cli.py
AutoChromedriver-2.2.1.dist-info/LICENSE
AutoChromedriver-2.2.1.dist-info/METADATA
AutoChromedriver-2.2.1.dist-info/WHEEL
AutoChromedriver-2.2.1.dist-info/entry_points.txt
AutoChromedriver-2.2.1.dist-info/top_level.txt
AutoChromedriver-2.2.1.dist-info/RECORD
