Metadata-Version: 1.1
Name: AutoChromedriver
Version: 2.2.1
Summary: Downloads and unzips chromedriver to curent directory
Home-page: https://github.com/joeyism/autochromedriver
Author: joeyism
Author-email: joeyism101@gmail.com
License: UNKNOWN
Download-URL: https://github.com/joeyism/autochromedriver2.2.1.tar.gz
Keywords: chromedriver,selenium,auto,automatic,download
Platform: UNKNOWN
